zaloapi/__init__.py
zaloapi/_client.py
zaloapi/_core.py
zaloapi/_exception.py
zaloapi/_message.py
zaloapi/_objects.py
zaloapi/_state.py
zaloapi/_threads.py
zaloapi/_util.py
zaloapi/models.py
zaloapi-0.0.1.dist-info/METADATA
zaloapi-0.0.1.dist-info/WHEEL
zaloapi-0.0.1.dist-info/top_level.txt
zaloapi-0.0.1.dist-info/RECORD
